[{"ID":18,"kullaniciAdi":"muro5759","degisiklikMiktari":-50.0,"islemTarihi":"2021-05-14T10:03:41.9405569+03:00","gerceklesmeTarihi":"2021-05-14T10:04:31.2781746+03:00","aciklama":"Bakiyeden Çekme İşlemi","incelendiMi":true,"onaylandiMi":true,"gerceklestiMi":true},{"ID":19,"kullaniciAdi":"muro5759","degisiklikMiktari":-5000.0,"islemTarihi":"2021-05-14T10:03:44.358549+03:00","gerceklesmeTarihi":"2021-05-14T10:04:11.7078444+03:00","aciklama":"Bakiyeden Çekme İşlemi","incelendiMi":true,"onaylandiMi":true,"gerceklestiMi":false},{"ID":20,"kullaniciAdi":"muro5759","degisiklikMiktari":-100.0,"islemTarihi":"2021-05-14T10:03:46.8144522+03:00","gerceklesmeTarihi":"2021-05-14T10:04:28.4873136+03:00","aciklama":"Bakiyeden Çekme İşlemi","incelendiMi":true,"onaylandiMi":true,"gerceklestiMi":true},{"ID":21,"kullaniciAdi":"muro5759","degisiklikMiktari":50.0,"islemTarihi":"2021-05-14T10:03:50.5019442+03:00","gerceklesmeTarihi":"2021-05-14T10:04:25.9488282+03:00","aciklama":"Bakiye Ekleme İşlemi","incelendiMi":true,"onaylandiMi":true,"gerceklestiMi":true},{"ID":22,"kullaniciAdi":"muro5759","degisiklikMiktari":-5000.0,"islemTarihi":"2021-05-14T10:04:35.7143276+03:00","gerceklesmeTarihi":"2021-05-14T10:04:38.834577+03:00","aciklama":"Bakiyeden Çekme İşlemi","incelendiMi":true,"onaylandiMi":true,"gerceklestiMi":false},{"ID":23,"kullaniciAdi":"muro5759","degisiklikMiktari":-50.0,"islemTarihi":"2021-05-14T10:04:41.5203968+03:00","gerceklesmeTarihi":"2021-05-14T10:04:47.7364216+03:00","aciklama":"Bakiyeden Çekme İşlemi","incelendiMi":true,"onaylandiMi":false,"gerceklestiMi":false},{"ID":24,"kullaniciAdi":"muro5759","degisiklikMiktari":-5000.0,"islemTarihi":"2021-05-14T10:06:40.4022742+03:00","gerceklesmeTarihi":"2021-05-14T10:16:52.8927919+03:00","aciklama":"Bakiyeden Çekme İşlemi","incelendiMi":true,"onaylandiMi":true,"gerceklestiMi":false},{"ID":25,"kullaniciAdi":"muro5759","degisiklikMiktari":-500.0,"islemTarihi":"2021-05-14T10:06:42.4944063+03:00","gerceklesmeTarihi":"2021-05-14T10:16:48.6915191+03:00","aciklama":"Bakiyeden Çekme İşlemi","incelendiMi":true,"onaylandiMi":true,"gerceklestiMi":false},{"ID":26,"kullaniciAdi":"muro5759","degisiklikMiktari":-50.0,"islemTarihi":"2021-05-14T10:16:21.9921316+03:00","gerceklesmeTarihi":"2021-05-14T10:16:44.5661757+03:00","aciklama":"Bakiyeden Çekme İşlemi","incelendiMi":true,"onaylandiMi":true,"gerceklestiMi":true},{"ID":27,"kullaniciAdi":"muro5759","degisiklikMiktari":100.0,"islemTarihi":"2021-05-14T10:16:28.970913+03:00","gerceklesmeTarihi":"2021-05-14T10:16:55.2784551+03:00","aciklama":"Bakiye Ekleme İşlemi","incelendiMi":true,"onaylandiMi":true,"gerceklestiMi":true},{"ID":28,"kullaniciAdi":"muro5759","degisiklikMiktari":-500.0,"islemTarihi":"2021-05-14T10:22:53.5461504+03:00","gerceklesmeTarihi":"2021-05-14T10:23:04.1092055+03:00","aciklama":"Bakiyeden Çekme İşlemi","incelendiMi":true,"onaylandiMi":true,"gerceklestiMi":true},{"ID":29,"kullaniciAdi":"muro5759","degisiklikMiktari":500.0,"islemTarihi":"2021-05-14T10:30:17.1460045+03:00","gerceklesmeTarihi":"2021-05-14T10:30:30.6820772+03:00","aciklama":"Bakiye Ekleme İşlemi","incelendiMi":true,"onaylandiMi":true,"gerceklestiMi":true},{"ID":30,"kullaniciAdi":"muro5759","degisiklikMiktari":-100.0,"islemTarihi":"2021-05-14T10:33:08.0591188+03:00","gerceklesmeTarihi":"2021-05-14T10:33:20.4299204+03:00","aciklama":"Bakiyeden Çekme İşlemi","incelendiMi":true,"onaylandiMi":true,"gerceklestiMi":true},{"ID":31,"kullaniciAdi":"muro5759","degisiklikMiktari":-50.0,"islemTarihi":"2021-05-14T10:38:32.0640364+03:00","gerceklesmeTarihi":"2021-05-14T10:38:46.5531634+03:00","aciklama":"Bakiyeden Çekme İşlemi","incelendiMi":true,"onaylandiMi":true,"gerceklestiMi":true},{"ID":32,"kullaniciAdi":"muro5759","degisiklikMiktari":-275.0,"islemTarihi":"2021-05-14T10:38:58.2181167+03:00","gerceklesmeTarihi":"2021-05-14T10:39:00.8285901+03:00","aciklama":"Bakiyeden Çekme İşlemi","incelendiMi":true,"onaylandiMi":true,"gerceklestiMi":true},{"ID":33,"kullaniciAdi":"muro5759","degisiklikMiktari":250.0,"islemTarihi":"2021-05-14T10:43:00.6700862+03:00","gerceklesmeTarihi":"2021-05-14T10:43:08.6275082+03:00","aciklama":"Bakiye Ekleme İşlemi","incelendiMi":true,"onaylandiMi":true,"gerceklestiMi":true},{"ID":34,"kullaniciAdi":"muro5759","degisiklikMiktari":50.0,"islemTarihi":"2021-05-14T17:36:33.1013457+03:00","gerceklesmeTarihi":"2021-05-14T17:36:39.9285971+03:00","aciklama":"Bakiye Ekleme İşlemi","incelendiMi":true,"onaylandiMi":true,"gerceklestiMi":true},{"ID":35,"kullaniciAdi":"muro5759","degisiklikMiktari":100.0,"islemTarihi":"2021-05-14T17:36:56.4794769+03:00","gerceklesmeTarihi":"2021-05-14T17:37:00.4044508+03:00","aciklama":"Bakiye Ekleme İşlemi","incelendiMi":true,"onaylandiMi":true,"gerceklestiMi":true},{"ID":36,"kullaniciAdi":"muro5759","degisiklikMiktari":50.0,"islemTarihi":"2021-05-14T17:39:59.4708376+03:00","gerceklesmeTarihi":"2021-05-14T17:40:12.0480437+03:00","aciklama":"Bakiye Ekleme İşlemi","incelendiMi":true,"onaylandiMi":true,"gerceklestiMi":true},{"ID":37,"kullaniciAdi":"muro5759","degisiklikMiktari":50.0,"islemTarihi":"2021-05-14T17:40:21.1065315+03:00","gerceklesmeTarihi":"2021-05-14T17:40:26.4922445+03:00","aciklama":"Bakiye Ekleme İşlemi","incelendiMi":true,"onaylandiMi":true,"gerceklestiMi":true},{"ID":38,"kullaniciAdi":"muro5759","degisiklikMiktari":275.0,"islemTarihi":"2021-05-14T17:42:24.0289285+03:00","gerceklesmeTarihi":"2021-05-14T17:42:57.2199684+03:00","aciklama":"Bakiye Ekleme İşlemi","incelendiMi":true,"onaylandiMi":false,"gerceklestiMi":false},{"ID":39,"kullaniciAdi":"muro5759","degisiklikMiktari":-500.0,"islemTarihi":"2021-05-14T17:42:28.6438687+03:00","gerceklesmeTarihi":"2021-05-14T17:43:09.8005027+03:00","aciklama":"Bakiyeden Çekme İşlemi","incelendiMi":true,"onaylandiMi":true,"gerceklestiMi":true},{"ID":40,"kullaniciAdi":"muro5759","degisiklikMiktari":-275.0,"islemTarihi":"2021-05-14T17:44:14.1854397+03:00","gerceklesmeTarihi":"2021-05-14T17:44:41.976593+03:00","aciklama":"Bakiyeden Çekme İşlemi","incelendiMi":true,"onaylandiMi":true,"gerceklestiMi":false},{"ID":41,"kullaniciAdi":"muro5759","degisiklikMiktari":1000.0,"islemTarihi":"2021-05-14T17:44:47.1823968+03:00","gerceklesmeTarihi":"2021-05-14T17:44:50.7540141+03:00","aciklama":"Bakiye Ekleme İşlemi","incelendiMi":true,"onaylandiMi":true,"gerceklestiMi":true},{"ID":42,"kullaniciAdi":"muro5759","degisiklikMiktari":-250.0,"islemTarihi":"2021-05-14T17:46:28.932571+03:00","gerceklesmeTarihi":"2021-05-14T17:46:34.5951026+03:00","aciklama":"Bakiyeden Çekme İşlemi","incelendiMi":true,"onaylandiMi":true,"gerceklestiMi":true},{"ID":43,"kullaniciAdi":"muro5759","degisiklikMiktari":-50.0,"islemTarihi":"2021-05-14T17:46:44.4526166+03:00","gerceklesmeTarihi":"2021-05-14T17:46:51.144483+03:00","aciklama":"Bakiyeden Çekme İşlemi","incelendiMi":true,"onaylandiMi":true,"gerceklestiMi":true},{"ID":44,"kullaniciAdi":"muro5759","degisiklikMiktari":-275.0,"islemTarihi":"2021-05-14T17:48:33.6169015+03:00","gerceklesmeTarihi":"2021-05-14T17:48:37.7219391+03:00","aciklama":"Bakiyeden Çekme İşlemi","incelendiMi":true,"onaylandiMi":true,"gerceklestiMi":true},{"ID":45,"kullaniciAdi":"muro5759","degisiklikMiktari":-275.0,"islemTarihi":"2021-05-14T17:53:28.5255843+03:00","gerceklesmeTarihi":"2021-05-14T17:53:36.1468468+03:00","aciklama":"Bakiyeden Çekme İşlemi","incelendiMi":true,"onaylandiMi":true,"gerceklestiMi":true},{"ID":46,"kullaniciAdi":"muro5759","degisiklikMiktari":-225.0,"islemTarihi":"2021-05-14T17:53:50.7177223+03:00","gerceklesmeTarihi":"2021-05-14T17:53:56.3283226+03:00","aciklama":"Bakiyeden Çekme İşlemi","incelendiMi":true,"onaylandiMi":true,"gerceklestiMi":true}]